ibanker/.DS_Store
ibanker/__init__.py
ibanker/sec_client/__init__.py
ibanker/sec_client/base.py
ibanker/sec_client/caller.py
ibanker/sec_client/client.py
ibanker/sec_client/dumper.py
ibanker/sec_client/extractor.py
ibanker/sec_client/formatter.py
ibanker/sec_client/loader.py
ibanker/tables/DATABASE.db
ibanker/tables/__init__.py
ibanker/tables/classifiers.py
ibanker/tables/data/ticks_and_ciks_db.json
ibanker/tables/inserter.py
ibanker/tables/query/__init__.py
ibanker/tables/query/base_query.py
ibanker/tables/query/query.py
ibanker/tables/query/query_parser.py
ibanker/tables/reset_db.py
ibanker/tables/tables.py
ibanker/tables/updater.py
ibanker/utils/__init__.py
ibanker/utils/sec_client_utils/__init__.py
ibanker/utils/sec_client_utils/_call_helpers.py
ibanker/utils/sec_client_utils/_duplicate_handlers.py
ibanker/utils/sec_client_utils/_extractor_utils.py
ibanker/utils/sec_client_utils/_value_handlers.py
ibanker/utils/sec_client_utils/time_helpers.py
ibanker/utils/sec_client_utils/zipper.py
ibanker/utils/valtools_utils/__init__.py
ibanker/utils/valtools_utils/forecast_utils.py
ibanker/valtools/.DS_Store
ibanker/valtools/__init__.py
ibanker/valtools/forecast.py
ibanker/valtools/forecasttools/__init__.py
ibanker/valtools/forecasttools/forecasting.py
ibanker/valtools/historicals.py
ibanker/valtools/histtools/__init__.py
ibanker/valtools/histtools/history.py
ibanker/valtools/histtools/returns.py
ibanker/valtools/ratios.py
ibanker/valtools/ratiotools/__init__.py
ibanker/valtools/ratiotools/basic.py
ibanker/valtools/risk.py
ibanker/valtools/risktools/__init__.py
ibanker/valtools/risktools/beta.py
ibanker/valtools/risktools/capm.py
ibanker/valtools/risktools/constants.py
ibanker/valtools/risktools/fred.py
ibanker/valtools/risktools/sp-500-historical-annual-returns.csv
ibanker/valtools/visualtools/__init__.py
ibanker/valtools/visualtools/plt_capm.py
ibanker-0.0.1.dist-info/LICENSE
ibanker-0.0.1.dist-info/WHEEL
ibanker-0.0.1.dist-info/METADATA
ibanker-0.0.1.dist-info/RECORD
