Metadata-Version: 2.1
Name: ibanker
Version: 0.0.1
Summary: IBanker is a package intended for building typical financial models used in investment banking i.e DCFs, LBOs, etc.
License: MIT
Keywords: Finance,Investment Banking,Financial Modeling,pandas,numpy
Author: _fiz_
Author-email: crxz.fiz@gmail.com
Requires-Python: >=3.9,<4.0
Classifier: Development Status :: 1 - Planning
Classifier: Intended Audience :: Financial and Insurance Industry
Classifier: License :: OSI Approved :: MIT License
Classifier: Operating System :: MacOS :: MacOS X
Classifier: Operating System :: Microsoft :: Windows :: Windows 10
Classifier: Programming Language :: Python
Classifier: Programming Language :: Python :: 3
Classifier: Programming Language :: Python :: 3.10
Classifier: Programming Language :: Python :: 3.9
Classifier: Topic :: Office/Business :: Financial
Classifier: Topic :: Office/Business :: Financial :: Investment
Classifier: Topic :: Office/Business :: Financial :: Spreadsheet
Provides-Extra: black
Requires-Dist: SQLAlchemy (>=1.4.40,<2.0.0)
Requires-Dist: cytools (>=0.4.1,<0.5.0)
Requires-Dist: fake-useragent (>=0.1.11,<0.2.0)
Requires-Dist: numpy (>=1.23.2,<2.0.0)
Requires-Dist: pandas (>=1.4.3,<2.0.0)
Requires-Dist: pandas-datareader (>=0.10.0,<0.11.0)
Requires-Dist: sec-edgar-api (>=1.0.0,<2.0.0)
Requires-Dist: tinydb (>=4.7.0,<5.0.0)
Requires-Dist: yfinance (>=0.1.74,<0.2.0)
